arch_release_promotion-0.3.0.post0.dist-info/METADATA
arch_release_promotion-0.3.0.post0.dist-info/WHEEL
arch_release_promotion-0.3.0.post0.dist-info/entry_points.txt
arch_release_promotion-0.3.0.post0.dist-info/licenses/LICENSE
arch_release_promotion/__init__.py
arch_release_promotion/argparse.py
arch_release_promotion/cli.py
arch_release_promotion/config.py
arch_release_promotion/files.py
arch_release_promotion/gitlab.py
arch_release_promotion/release.py
arch_release_promotion/signature.py
arch_release_promotion/torrent.py
arch_release_promotion-0.3.0.post0.dist-info/RECORD
