Metadata-Version: 2.1
Name: arch-release-promotion
Version: 0.3.0.post0
Summary: Promote official Arch Linux releases and synchronize them
Keywords: arch linux releases pgp signature synchronization torrent
Home-page: https://gitlab.archlinux.org/archlinux/arch-release-promotion
Author-Email: David Runge <dvzrv@archlinux.org>
License: GPL-3.0-or-later
Classifier: Development Status :: 3 - Alpha
Classifier: Intended Audience :: Developers
Classifier: Natural Language :: English
Classifier: Operating System :: POSIX :: Linux
Classifier: Topic :: Security :: Cryptography
Classifier: Topic :: Software Development
Classifier: Topic :: System :: Operating System
Classifier: Topic :: Utilities
Project-URL: Bug tracker, https://gitlab.archlinux.org/archlinux/arch-release-promotion/-/issues/
Project-URL: Homepage, https://gitlab.archlinux.org/archlinux/arch-release-promotion
Project-URL: Repository, https://gitlab.archlinux.org/archlinux/arch-release-promotion
Project-URL: Documentation, https://gitlab.archlinux.org/archlinux/arch-release-promotion/-/blob/master/README.rst
Requires-Python: <4.0,>=3.10
Requires-Dist: pydantic<3.0.0,>=2.0.0
Requires-Dist: python-dotenv<2.0.0,>=1.0.0
Requires-Dist: pyxdg<1.0,>=0.27
Requires-Dist: email-validator<3.0.0,>=2.0.0
Requires-Dist: torrentool<2.0.0,>=1.1.1
Requires-Dist: python-gitlab<4.0.0,>=3.0.0
Requires-Dist: orjson<4.0.0,>=3.6.1
Requires-Dist: prometheus-client<1.0.0,>=0.14.1
Requires-Dist: tomli>=2.0.1; python_version < "3.11"
Requires-Dist: pydantic-settings>=2.0.2
